MANIFEST.in
README.md
setup.cfg
setup.py
python_logger/__init__.py
python_logger/logger.py
python_logger.egg-info/PKG-INFO
python_logger.egg-info/SOURCES.txt
python_logger.egg-info/dependency_links.txt
python_logger.egg-info/not-zip-safe
python_logger.egg-info/top_level.txt
tests/__init__.py
tests/test_logger.py