Metadata-Version: 2.1
Name: python-logger
Version: 0.0.1
Summary: Wrapper around standard python logging implementing additional features.
Home-page: https://git.dtone.xyz/data/python_logger
Author: Adam Cincura
Author-email: cz.data@dtone.com
License: UNKNOWN
Keywords: python logger mdc
Platform: UNKNOWN
Classifier: Programming Language :: Python :: 3.7
